noformat/__init__.py
noformat/formats.py
noformat/main.py
noformat/utils.py
noformat-0.1.4.dist-info/DESCRIPTION.rst
noformat-0.1.4.dist-info/METADATA
noformat-0.1.4.dist-info/RECORD
noformat-0.1.4.dist-info/WHEEL
noformat-0.1.4.dist-info/metadata.json
noformat-0.1.4.dist-info/top_level.txt
