Metadata-Version: 2.0
Name: noformat
Version: 0.1.4
Summary: save and load a structured collection of data as folder
Home-page: https://github.com/Palpatineli/noformat
Author: Keji Li
Author-email: mail@keji.li
License: GPLv3
Download-URL: https://github.com/Palpatineli/noformat/archive/0.1.4.tar.gz
Platform: UNKNOWN
Classifier: Programming Language :: Python :: 3.5
Classifier: Programming Language :: Python :: 3.6
Classifier: License :: OSI Approved :: GNU General Public License v3 (GPLv3)
Provides-Extra: pd
Requires-Dist: numpy
Provides-Extra: pd
Requires-Dist: pandas; extra == 'pd'
